[
    {
        "Author": "pqpqpq1",
        "Title": "[商品] 7-11牛丼",
        "Score": "85",
        "Content": " 從它出來到現在其實我已經觀望很久了XD 但是因為有人說他會很鹹所以遲遲不敢下手 今天終於下定決心要敗下它了!!! 所以再吃他之前我先試了一下醬汁的鹹度 恩   OK 然後再將牛肉倒到碗裡   留了一點醬與預防萬一 攪拌了之後    我覺得蠻好吃的耶(L)   就把剩下的醬汁全部到進碗裏了 可能是我比較不挑吧@@ 醬是有點鹹鹹甜甜的  南部口味? 總之是沒讓我失望 但是價格依舊很不親民阿!!!"
    },
    {
        "Author": "flowerheart",
        "Title": "[商品] 法式主廚白醬野蔬嫩雞燴炒飯",
        "Score": "",
        "Content": " 打開的第一印象，和之前全家出的也是白醬的那款飯好像 分數是和之前那款做比較得出的結論，完全比不上那款， 但因為我肚子很餓所以還是有及格分XD 飯單吃的話，對重口味來說偏淡，但是加上白醬後就變的很鹹， 雞肉很少，蔬菜也很少，紅蘿蔔和上二個比就多一點XD 大胃口的人來說份量沒辦法飽，但可以墊肚子 價格不太美，下次應該不會選擇購買。"
    },
    {
        "Author": "aquarian",
        "Title": "[商品] 全家-豉椒臭豆腐",
        "Score": "85",
        "Content": "      知名餐廳的一道人氣菜餚，居然靜靜的躺在全家便利商店的冷凍櫃裡      版上也沒有任何討論，真的讓我太訝異了      剛剛微波完，趁熱吃      覺得味道還不錯，但湯頭有點鹹      也許是怕微波過頭，湯會爆出      所以只有盒子高度的三分之一不到      下次吃加一點熱開水，應該會更棒"
    },
    {
        "Author": "pk30401",
        "Title": "[商品] 孔雀香酥脆 濃起司",
        "Score": "80",
        "Content": " 從以前就很愛吃孔雀香酥脆了 只是以前最早只有香魚口味 現在多了辛七味跟濃起司兩種 在小7看到就馬上買一了包 剛入手就看到很搞笑的封面XDDDDDDDD 味道方面 其實起司味並不是很濃 甚至可以說是很淡 建議廠商把濃這個字去掉 雖然起司味沒很濃 但我覺得還是蠻好吃的啦 甜甜鹹鹹的 沒有特別突出 算中規中矩 至少沒有辜負我的期望 回購率大概70% 給大家當參考囉"
    },
    {
        "Author": "arancione",
        "Title": "[商品] 7-11 雞蓉玉米燕麥粥",
        "Score": "90",
        "Content": " 天氣冷最適合吃粥了           包裝標榜著\"三寶燕麥使用\"，感覺好健康(我是需要降膽固醇的人XD)           打開一看，料出乎意料的很豐富           因為加了三寶(小薏仁跟燕麥跟大燕麥之類的?)           玉米跟雞肉的量也蠻多的           粥很濃稠，吃起來有非常淡的胡椒味，玉米粒很甜，好好吃~           對胃口不大的人來說份量剛好，而且才148卡           現在買打完折才31元，蠻划算的，推薦！"
    }
]