[
    {
        "Author": "aaaa9858",
        "Title": "[商品] 7-11 辣味炸雞球",
        "Score": "9060",
        "Content": "                 一直想吃這款但苦無機會 XD                 今天終於一嘗宿願                 我是買回家用烤箱烤的                 大概是200度烤了五、六分鐘                 外皮金黃酥脆、肉又香嫩可口                 是有點辣 但吃過三塊就適應了                 我覺得比肯爺爺的雞米花好吃                 而且又不貴~"
    },
    {
        "Author": "chiyu2236",
        "Title": "[商品] 全家 夯番薯",
        "Score": "95",
        "Content": "   這幾天天氣好冷   吃完飯總想要來個甜點   之前有吃過全家跟ok的烤番薯   吃起來都是綿綿鬆鬆的番薯   但是感覺好像沒有烤得很到位   這次全家的夯番薯廣告打超大   讓我想要再給便利商店的烤番薯一次機會   爬了一下版上   有版大說可以微波之後再吃  比較不會遇到不熟的情形   所以我選了一個大小剛好的番薯請店員幫我微波秤重   大約25元~~~   價格算合理(前幾天在外面買攤販   回家後迫不及待地剖半吃   這次全家的番薯真的不一樣耶~~   是蜜地瓜的烤番薯   金黃色帶點焦糖的外貌   讓人驚為天人   超好吃的^^   推薦大家到全家去吃看看喔~~~"
    }
]