[
    {
        "Author": "jujusun",
        "Title": "[商品] 7-11 新工法火腿三明治",
        "Score": "90",
        "Content": " 照片 新工法的三明治 吐司的確比之前鬆軟有嚼勁 更令人驚喜的是裡面的配料都很飽滿 整體比那個香港人狂熱的三明治有得比的感覺 很好吃"
    },
    {
        "Author": "jujusun",
        "Title": "[商品] 7-11櫻花蝦蛋酥拌飯",
        "Score": "90",
        "Content": " 照片  打開便當就有好香的櫻花蝦香味 整體價格合理 番茄炒蛋很甜好吃 整體蠻好吃的 還會想再買"
    },
    {
        "Author": "Jiapie",
        "Title": "[商品] 義美 低糖豆奶",
        "Score": "80",
        "Content": " 最近比較少試飲料，因為常去的小７最近沒有想試的飲料                   （乳牛先生、36法朗的可可亞）冏rz                   對豆奶沒有特別偏好，大多是買來加紅茶 >///<  不過新                   聞寫說它賣的很好，所以跟風試一下味道；並沒有太出乎                   意料的味道啦~ 就是很永和豆漿那種味道，這次選低糖的                   沒那麼甜；喝下去的感覺還不錯，不會膩的口感，會想回                   購的產品 ^^"
    },
    {
        "Author": "sunkelsa",
        "Title": "[商品] 7-11 蔬果和風醬燒肉飯",
        "Score": "80",
        "Content": " 外觀看起來很好吃（肉食主義者），所以就買來試試看。 　　　　　燒肉算給得很大方鋪得滿滿的，上面還有灑芝麻， 　　　　　肉也還不錯，有瘦有肥剛好，不會太油膩也不會柴。 　　　　　醬汁甜甜的搭配起來滿好吃（雖然吃不出特別標示的蘋果味）。 　　　　　米飯有醬料滿入口的，沒有粒粒分明但是也不會軟爛。 　　　　　泡菜味道不太好（但是我本來就不吃泡菜，分辨不出來）           整體飯量偏少，但是也吃得飽。份量適合本來就吃不多的人"
    },
    {
        "Author": "lovelibear",
        "Title": "[商品] 全家 典藏比利時巧克力霜淇淋",
        "Score": "75",
        "Content": " 先上商品圖  前半部吃起來真的頗濃 含在嘴裡有一點點的可可苦不過很淡 反而襯托出巧克力的濃&甜 OREO餅乾就是OREO餅乾 老實說我覺得餅乾尬巧克力霜淇淋有點失算 已經很濃的冰吃完餅乾後一整個感覺膩了 所以剩下半杯在感覺膩的味覺中消化完畢 化工味倒是還好雖然巧克力味真的 超。濃 可是很像在吃一大袋costco松露巧克力的感覺 真心推薦要吃綜合 但我買的這間只有賣巧克力口味就無法 或者餅乾可以不要用OREO 吃到後來會變得很像吃牛奶糖還幫你淋煉乳一樣痛苦"
    },
    {
        "Author": "Jiapie",
        "Title": "[商品] 純萃喝咖啡(白巧克力咖啡飲品)",
        "Score": "65",
        "Content": " 上市一陣子了，品名看起來有特殊一點點（白巧克力咖啡）                   又是巧克力又是咖啡的，預期覺得會有點膩；結果也還好                   味道和咖啡牛奶有點像不難喝，可是也不會特別去選擇它。"
    }
]