[
    {
        "Author": "Jiapie",
        "Title": "[商品] 統一蜜豆奶（雞蛋口味）",
        "Score": "",
        "Content": "  （大家都喝過了吧？再寫分數怪怪的 ^^）         "
    },
    {
        "Author": "colin1120",
        "Title": "[商品] 全家 中華小籠湯包、義式番茄蔬菜濃湯麵",
        "Score": "85",
        "Content": " 湯包的味道還不錯 不過還是算普通 湯汁不少 咬的時候注意一下 嘴巴閉稍微緊一點 可能會噴出來 (這害我擦了一遍鍵盤 不過這不是湯包的問題 不扣分) 唯一的問題點是 它的湯汁可能會在微波之後流出來 所以拿的時候一定要平的拿 否則打開外包裝的時候就慘了 要請店員微波時注意一下 這個價格買這樣的湯包感覺其實很棒"
    },
    {
        "Author": "orcadan",
        "Title": "[商品] OK 霜淇淋",
        "Score": "85",
        "Content": "  10月初到11月剛好有特價檔期 原價30的冰,每周四五六日都20元 剛好我這附近有看到一家,就買來吃了~ 口感偏鬆軟綿密,不是-4那種硬梆梆的紮實款 吃起來甜度是比全家輕,個人挺喜歡的 大小則是五圈,雖然也是中空但挺大隻的 杯子拿到的不是廣告那樣,我拿到的是一圈圈小圈的多拿之甜甜圈杯 吃起來脆度夠也沒吃到奇怪的油耗味XD 特價期有一整個月,回購機率蠻高的 9  然後這是據點參考,不過真的是僅供參考"
    }
]