[
    {
        "Author": "wunimo",
        "Title": "[商品] 萊爾富-和風牛丼飯",
        "Score": "68",
        "Content": " 之前曾經耳聞萊爾富的蓋飯很好吃 尤其牛丼蠻多人推薦的 但那時候找了很多家萊爾富 都找不到 昨天看到我家樓下的萊爾富有了和風牛丼是新產品 今天中午就順道買來吃 大概440g 790kacl 味道真的還算還不錯啦 不過因為飯份量多 就顯得牛肉片較少 配料還有洋蔥 會覺得有點單調 以65元價格同是超商微波食品我會選擇便當類的"
    },
    {
        "Author": "hoyumi",
        "Title": "[商品] 牛蒡沙拉大對決-全家vs萊爾富(外加之前小七產品)",
        "Score": "55",
        "Content": "  ============================================================ 【商品名稱/價格】：芝麻牛蒡沙拉 【便利商店/廠商名稱】：全家 【規格/內容物/熱量】：牛蒡 蔬菜 美乃滋 芝麻醬 白芝麻 黑芝麻"
    },
    {
        "Author": "hoyumi",
        "Title": "Re: [商品] 全家辣油系列商品第六款(辣油豬肉飯糰)",
        "Score": "80",
        "Content": "  這次的全家辣油商品都不錯 這次吃了上次沒吃到的飯糰 果然跟網友說的一樣 辣肉醬很像新東陽那種 而且很難得全家的米飯可以沒有失敗 唯一的缺點是有點容易漏油 不過這款還不錯就是了"
    },
    {
        "Author": "alien01",
        "Title": "[商品] 泰山 蕃茄蜜晶凍",
        "Score": "9",
        "Content": "   本人今天也在因緣際會之下買了這款飲料來喝   其實我是滿喜歡蕃茄汁的，從以前鐵罐可果美的時候就很愛喝了！   以前也有喝過這系列的其他果汁，想說應該都還OK吧？   結果喝下去的感覺出乎意料的詭異 = =   雖然整罐裡面固體的「料」還滿多的，   可是蕃茄味道不蕃茄，甜不甜、鹹不鹹的，是一個很人工的怪味！   緊接著，這怪味蕃茄加上椰果果凍，就變成非常奇怪的口感！   因為怪味蕃茄汁，讓我有一種咬破嘴巴之後留了滿嘴鮮血的感覺，   再嚼著那軟不軟硬不硬的椰果   我好像在咬自己的痰阿！！！！   吞下去的瞬間就像是感冒重病的我正從鼻腔吸著夾雜血液的鼻涕一樣   哎～早知道應該拿桂格燕麥的，   人工蕃茄實在無法令我開懷"
    }
]