[
    {
        "Author": "benq1620",
        "Title": "Re: [商品] 7-11黑雷神巧克力",
        "Score": "90",
        "Content": " 看到e-shopping版的討論後，就立馬去買來吃~ :           小小一個要15元，還是覺得有點貴~ :           但口感還不錯，有一點小甜，但是喜歡吃甜的我，覺得很好吃~ :           下次來試試來紅雷神~ :           喜歡吃巧克力的捧油可以去試試看~或許會愛上哦~ 之前在臉書拿到的序號還有剩7組 有鄉民想試吃的話,前7位推文者 送你一組,吃完記得PO一下心得或 推一下文吧!!"
    },
    {
        "Author": "htthgt",
        "Title": "[商品] 萊爾富-無骨牛小排蓋飯",
        "Score": "75",
        "Content": " 剛剛突然肚子餓           宿舍對面剛好有間萊爾富           所以就買了這個蓋飯           我的食量有點大           這個分量算還可以           至於味道           醬的味道很像蘑菇醬           但還不難吃           75有點小貴QQ           順便問一下           萊爾富的冷凍食品有啥比較好吃的嗎?"
    },
    {
        "Author": "hoyumi",
        "Title": "[商品] 全家卡啦雞腿堡/醬燒豬排堡",
        "Score": "20",
        "Content": "  ========================================================================== 【商品名稱/價格】：醬燒豬排堡 【便利商店/廠商名稱】：全家 【規格/內容物/熱量】：漢堡麵包 豬肉 油 蔬菜 豬排醬 美乃滋"
    },
    {
        "Author": "watteppei",
        "Title": "[商品] UCC香蕉咖啡牛奶",
        "Score": "70",
        "Content": " 今天特早起床 去新開的全家買早餐 本來想買咖啡牛奶 找不到才想到咖啡牛奶是7-11賣的~口~ 但還是想喝咖啡提神 看到UCC的香蕉咖啡 想起板上不太OK的評論 還是拿他旁邊的黑糖好了 可是我是勇於嘗試 不太怕難喝飲料的人! 所以思考一秒還是拿了香蕉!!(好拉~其實是覺得它黃色的包裝好可愛///) 回家後吸管一插 用力吸了一口 恩!!!!好濃的香蕉~~~~~香料味囧 跟泰國Pocky香蕉口味一樣!! 但我喜歡泰國香蕉Pocky  所以這是我喜歡的口味 整體來說偏甜咖啡味淡 評價差是正常的 只能賣給一些喜歡奇怪口味的人 例如原PO 可能過陣子就會消失在架上了"
    }
]