[
    {
        "Author": "kexi0711",
        "Title": "[商品] 全家 早。健康蔬果汁 (活力加乘)",
        "Score": "0",
        "Content": " 繼小七的手搖風紅茶拿鐵之後第二款讓我喝不下第二口的飲料 記得上年剛推出的時候明明這系列的每一款都很好喝阿 之後突然消失了一陣子，最近又發現換了包裝復出了 開開心心的買了一罐來喝 囧 消失的期間到底出了什麼問題阿(難過)"
    },
    {
        "Author": "HankSu",
        "Title": "[商品] 全家 波爾多紅酒牛肉燴炒飯",
        "Score": "60",
        "Content": " 跟7-11的燴飯一樣料好少 大部分入口時都只有醬跟飯 兩三口才配到一片肉 吃完沒什麼飽足感 只覺得渴 因為那個紅酒燴牛肉的醬很鹹"
    },
    {
        "Author": "raesmile",
        "Title": "[商品] open長崎蜂蜜蛋糕",
        "Score": "85",
        "Content": "  本身是不太愛甜食的人  但這款冰進冰箱後真的是一千兩百萬好吃(誇張了)  咬起來是比一般蜂蜜蛋糕再紮實一點的口感  稍微有點黏牙  雖然有點偏甜但不知為何整體就是深得我心  冰冰涼涼的吃起來讓人心情很好"
    }
]