[
    {
        "Author": "dodo7628",
        "Title": "[商品] 全家超麵包~紅豆核桃",
        "Score": "85",
        "Content": " 昨天晚上看到楊丞琳新廣告立馬決定要買來吃吃看           我超愛紅豆+核桃                       麵包表皮成十字型，跟一般傳統加上黑芝麻的不同           還有核桃點綴，光是打開看 就有小驚艷一下!                      麵包的Q度跟膨鬆度都有出來           天然酵母麵包很軟綿，吃起來有淡淡麵包香氣、有嚼勁           幾乎每一口都可以吃到濃厚紅豆泥跟核桃           以不到30價格，內餡的份量算是有誠意                      十勝紅豆餡吃起來 甜度適中           跟傳統麵包店的比，吃起來餡料更綿密 紅豆蠻扎實的           另外核桃顆粒大小剛好           紅豆泥跟核桃就是很搭阿~           傳統紅豆麵包  有時候多吃幾口 就會太甜膩           但可能是因為有核桃的關係，口味上比較有變化           紅豆泥不會太乾，當早餐吃 配咖啡剛好           以女生正常的胃口來說，一個剛好可以吃飽的量           下次回購率 : 90%"
    },
    {
        "Author": "Jiapie",
        "Title": "[商品] 波蜜 水果豐味~特調森巴 蔬果汁飲料",
        "Score": "70",
        "Content": " 打這對原料的時候，腦中閃過一個詞叫『貴夫人』；                    不過波蜜在這方面應該是很有經驗的，應該不會變成什麼                    失敗的“創意料理”；味道就是大部份果菜和在一起的味道，                    芭樂味稍重，不會過甜，不難喝，不過也沒什麼“新口味”的                    感覺。"
    }
]