[
    {
        "Author": "sikadear",
        "Title": "[商品] 7-11蕃茄牛肉湯",
        "Score": "50",
        "Content": " 突然想喝熱湯，關東煮又收起來了，無奈之下選了這看起來雷雷的， 喝完後果然很雷，就蕃茄湯+肉屑，肉完全沒存在感，我在餓的時候果然都會做蠢事 50塊如果能買關東煮早就2包麵+3樣料了 也只能怪自己犯賤 最後想問一下7-11有推薦的湯嗎??"
    },
    {
        "Author": "piyoko90",
        "Title": "[商品] 全家 乳牛香草蛋糕",
        "Score": "75",
        "Content": " 多圖網誌版： 全家這次推出的兩款動物紋蛋糕 乳牛香草蛋糕   豹紋咖啡巧克力蛋糕 不得不說外表真的很像東京芭娜娜! 左下的TOKYO CAKE 是 在上品架上亮眼的粉紅色及寶藍色非常顯眼 連廣告牌上都強打此兩款動物紋蛋糕 身為乳牛紋控的我 厚度大概是兩公分左右 乳牛紋的黑色部分是添加了\" 竹炭粉 \" 中間的夾心是香草鮮奶油 阿 蛋糕吃起來不會太甜 不過本身不是很愛此款的香草鮮奶油 此款蛋糕的外觀吸引力大於內容物  ! 下次可能會考慮買豹紋蛋糕 巧克力奶油內餡應該不錯 "
    },
    {
        "Author": "Jiapie",
        "Title": "[商品] 黑松 好茶哉甘韻烏龍",
        "Score": "70",
        "Content": " 其實好一點的茶不用加糖也會很好喝，不過罐裝飲料通常                 不歸類為“好茶”大部份不加糖其實都不是很好喝；甚至會覺得                 味道不只偏淡還說不出的怪，所以看到無糖有點擔心；結果是還                 好不難喝，在可接受範圍。^^                 補充一下，喝的時候一直覺得似曾相似？覺得如果加點糖搞不好                 會很像，冷泡茶微糖的那款烏龍；這樣會很跳tone嗎？ Orz"
    }
]